{
	"pages": [ //pages数组中第一项表示应用启动页，参考：https://uniapp.dcloud.io/collocation/pages
		{//路由自动配置
			"path": "pages/index/index",
			"style": {
				"navigationBarTitleText": "uni-app"
			}
		},
		{
			"path" : "pages/about/about",
			"style" : 
			{
				"navigationBarTitleText" : "关于",//默认导航栏头部
				"enablePullDownRefresh" : false//下拉刷新默认关闭
			}
		}
	],
	"globalStyle": {
		"navigationBarTextStyle": "black",
		"navigationBarTitleText": "uni-app",
		"navigationBarBackgroundColor": "#F8F8F8",
		"backgroundColor": "#F8F8F8"
	},
	"uniIdRouter": {}
}
